MANIFEST.in
README
setup.py
./django_yaba/__init__.py
./django_yaba/admin.py
./django_yaba/feeds.py
./django_yaba/fields.py
./django_yaba/forms.py
./django_yaba/models.py
./django_yaba/multiquery.py
./django_yaba/tests.py
./django_yaba/urls.py
./django_yaba/views.py
./django_yaba/widgets.py
./django_yaba/templatetags/__init__.py
./django_yaba/templatetags/get_setting.py
./django_yaba/templatetags/navbar.py
./django_yaba/templatetags/tweet.py
django_yaba.egg-info/PKG-INFO
django_yaba.egg-info/SOURCES.txt
django_yaba.egg-info/dependency_links.txt
django_yaba.egg-info/requires.txt
django_yaba.egg-info/top_level.txt
django_yaba/fixtures/initial_data.json
django_yaba/media/images/delicious.gif
django_yaba/media/images/digg.gif
django_yaba/media/images/reddit.gif
django_yaba/media/images/stumble-upon.jpg
django_yaba/media/js/jquery-1.3.2.min.js
django_yaba/media/js/jquery.js
django_yaba/media/js/slide.js
django_yaba/media/js/textareas.js
django_yaba/media/themes/default/css/bg_blue.gif
django_yaba/media/themes/default/css/bg_blue.gif.ORIG
django_yaba/media/themes/default/css/layout.css
django_yaba/media/themes/default/css/main.css
django_yaba/media/themes/default/css/patch_layout.css
django_yaba/media/themes/default/css/screen/basemod.css
django_yaba/media/themes/default/css/screen/content.css
django_yaba/media/themes/default/css/screen/images/bg_blue.gif
django_yaba/media/themes/default/css/screen/images/bg_blue.gif.ORIG
django_yaba/media/themes/default/images/bg_header.gif
django_yaba/media/themes/default/images/bg_header.gif.ORIG
django_yaba/media/themes/default/js/f4nt.js
django_yaba/media/themes/default/js/jquery-1.3.2.min.js
django_yaba/media/themes/default/js/jquery.js
django_yaba/media/themes/default/yaml/central_draft.css
django_yaba/media/themes/default/yaml/markup_draft.html
django_yaba/media/themes/default/yaml/add-ons/microformats/microformats.css
django_yaba/media/themes/default/yaml/add-ons/microformats/images/external_link.gif
django_yaba/media/themes/default/yaml/add-ons/microformats/images/hcalendar.png
django_yaba/media/themes/default/yaml/add-ons/microformats/images/hcard.png
