Metadata-Version: 1.0
Name: django-yaba
Version: 0.2.7
Summary: Yet Another Blog Application
Home-page: http://www.f4ntasmic.com
Author: Mark Rogers
Author-email: f4nt@f4ntasmic.com
License: BSD License
Keywords: django yaba blog
Platform: UNKNOWN
Classifier: Intended Audience :: Developers
Classifier: License :: OSI Approved :: BSD License
Classifier: Programming Language :: Python
